{
  "camera": {
    "origin": [13, 2, 3],
    "target": [0, 0, 0],
    "vup": [0, 1, 0],
    "vfov": 20,
    "aspect_ratio": 1.78,
    "aperture": 0,
    "focus_distance": -1
  },
  "materials": {
    "checker": {
      "type": "Diffuse",
      "texture": {
        "type": "Checker",
        "size": 10,
        "t1": {
          "type": "SolidColor",
          "color": [0.2, 0.3, 0.1]
        },
        "t2": {
          "type": "SolidColor",
          "color": [0.9, 0.9, 0.9]
        }
      }
    }
  },
  "world": [
    {
      "type": "Sphere",
      "center": [0, -10, 0],
      "radius": 10,
      "material": "checker"
    },
    {
      "type": "Sphere",
      "center": [0, 10, 0],
      "radius": 10,
      "material": "checker"
    }
  ]
}
